README.md
licence.txt
setup.py
harvest_indices/__init__.py
harvest_indices/indices.py
harvest_indices/utils.py
harvest_indices.egg-info/PKG-INFO
harvest_indices.egg-info/SOURCES.txt
harvest_indices.egg-info/dependency_links.txt
harvest_indices.egg-info/requires.txt
harvest_indices.egg-info/top_level.txt