Metadata-Version: 2.1
Name: harvest-indices
Version: 0.0.1
Summary: Calculate harvest anomalies from historical harvest data.
Author: Florian Ellsäßer
Author-email: info@cropdata.de
License: CC BY-NC-SA
Platform: UNKNOWN
License-File: licence.txt
